collecting_data/__init__.py
collecting_data/example.py
collecting_data-2.0.dist-info/METADATA
collecting_data-2.0.dist-info/WHEEL
collecting_data-2.0.dist-info/top_level.txt
collecting_data-2.0.dist-info/RECORD
