Metadata-Version: 2.1
Name: collecting_data
Version: 2.0
Summary: Project2
Author: Rasheed
Classifier: Programming Language :: Python :: 3
Requires-Python: >=3.8
